gadma/Inference.py
gadma/__init__.py
gadma/get_confidence_intervals.py
gadma/get_confidence_intervals_for_ld.py
gadma/precompute_ld_data.py
gadma/run_ls_on_boot_data.py
gadma/test.fs
gadma/cli/__init__.py
gadma/cli/arg_parser.py
gadma/cli/citations.py
gadma/cli/example_params
gadma/cli/extra_params_template
gadma/cli/params_template
gadma/cli/settings.py
gadma/cli/settings_storage.py
gadma/cli/test_settings
gadma/code_generator/__init__.py
gadma/code_generator/dadi_generator.py
gadma/code_generator/generator.py
gadma/code_generator/moments_generator.py
gadma/code_generator/moments_ld_generator.py
gadma/code_generator/momi_generator.py
gadma/core/__init__.py
gadma/core/core.py
gadma/core/core_run.py
gadma/core/draw_and_generate_code.py
gadma/core/shared_dict.py
gadma/data/__init__.py
gadma/data/data.py
gadma/data/data_utils.py
gadma/engines/__init__.py
gadma/engines/dadi_engine.py
gadma/engines/dadi_moments_common.py
gadma/engines/demes_engine.py
gadma/engines/engine.py
gadma/engines/moments_engine.py
gadma/engines/moments_ld_engine.py
gadma/engines/momi_engine.py
gadma/models/__init__.py
gadma/models/custom_demographic_model.py
gadma/models/demographic_model.py
gadma/models/event.py
gadma/models/model.py
gadma/models/structure_demographic_model.py
gadma/models/tree_demographic_model.py
gadma/models/variables_combinations.py
gadma/optimizers/__init__.py
gadma/optimizers/bayesian_optimization.py
gadma/optimizers/combinations.py
gadma/optimizers/gaussian_process.py
gadma/optimizers/genetic_algorithm.py
gadma/optimizers/global_optimizer.py
gadma/optimizers/linear_constrain.py
gadma/optimizers/local_optimizer.py
gadma/optimizers/optimizer.py
gadma/optimizers/optimizer_result.py
gadma/optimizers/smac_optim.py
gadma/utils/__init__.py
gadma/utils/distributions.py
gadma/utils/utils.py
gadma/utils/variable_pool.py
gadma/utils/variables.py
gadma-2.0.3.dist-info/licenses/LICENSE
gadma-2.0.3.dist-info/METADATA
gadma-2.0.3.dist-info/WHEEL
gadma-2.0.3.dist-info/entry_points.txt
gadma-2.0.3.dist-info/top_level.txt
gadma-2.0.3.dist-info/RECORD
