Metadata-Version: 2.4
Name: gadma
Version: 2.0.3
Summary: A tool for easy-to-use demographic inference
Home-page: https://github.com/ctlab/GADMA
Author: Ekaterina Noskova
Author-email: ekaterina.e.noskova@gmail.com
License: GNU GPLv3+
Project-URL: Documentation, https://gadma.readthedocs.io/en/stable/
Project-URL: Source Code, https://github.com/ctlab/GADMA
Project-URL: Bug Tracker, https://github.com/ctlab/GADMA/issues
Keywords: demographic history,demographic inference,evolution,population genetics
Classifier: Development Status :: 5 - Production/Stable
Classifier: Intended Audience :: Developers
Classifier: License :: OSI Approved :: GNU General Public License v3 or later (GPLv3+)
Classifier: Operating System :: POSIX :: Linux
Classifier: Operating System :: Microsoft :: Windows
Classifier: Operating System :: MacOS :: MacOS X
Classifier: Programming Language :: Python :: 3
Classifier: Programming Language :: Python :: 3.7
Classifier: Programming Language :: Python :: 3.8
Classifier: Programming Language :: Python :: 3.9
Classifier: Programming Language :: Python :: 3.10
Classifier: Topic :: Scientific/Engineering
Classifier: Topic :: Scientific/Engineering :: Bio-Informatics
Requires-Python: >=3.6
License-File: LICENSE
Requires-Dist: scipy
Requires-Dist: numpy
Requires-Dist: matplotlib
Requires-Dist: Pillow>=4.2.1
Requires-Dist: ruamel.yaml==0.16.12
Requires-Dist: demes
Requires-Dist: demesdraw
Requires-Dist: dadi
Requires-Dist: h5py==3.10.0
Requires-Dist: scikit-allel
Requires-Dist: moments-popgen
Requires-Dist: pandas<=2.2.2
Dynamic: license-file
